mixpopid/__init__.py
mixpopid/mixpopid.py
mixpopid-0.1.7.dist-info/LICENSE
mixpopid-0.1.7.dist-info/METADATA
mixpopid-0.1.7.dist-info/WHEEL
mixpopid-0.1.7.dist-info/top_level.txt
mixpopid-0.1.7.dist-info/RECORD
