Metadata-Version: 2.1
Name: mixpopid
Version: 0.1.7
Summary: Mixed leukemic tumor cell population identification 
Home-page: https://github.com/Apollinaria45/mixpopid
Author: Polina Arsenteva
Author-email: apolinaria10@mail.ru
License: MIT
Platform: UNKNOWN
Classifier: License :: OSI Approved :: MIT License
Classifier: Programming Language :: Python
Classifier: Programming Language :: Python :: 3
Classifier: Programming Language :: Python :: 3.6
Classifier: Operating System :: OS Independent
Requires-Python: >=3.5.0
Requires-Dist: scipy
Requires-Dist: matplotlib
Requires-Dist: numpy
